enadepy/__init__.py
enadepy/frequent.py
enadepy/helpers.py
enadepy/index.py
enadepy/loaders.py
enadepy/transform.py
enade_py-0.1.0.dist-info/AUTHORS.rst
enade_py-0.1.0.dist-info/LICENSE.txt
enade_py-0.1.0.dist-info/METADATA
enade_py-0.1.0.dist-info/WHEEL
enade_py-0.1.0.dist-info/top_level.txt
enade_py-0.1.0.dist-info/RECORD
