Metadata-Version: 2.1
Name: enade-py
Version: 0.1.0
Summary: A library for facilitating data analysis over Enade microdata
Home-page: https://github.com/mchoji/enade-py
Author: M. Choji
Author-email: mchoji@users.noreply.github.com
License: mit
Project-URL: Documentation, https://enade-py.readthedocs.io
Platform: any
Classifier: Development Status :: 4 - Beta
Classifier: Environment :: Console
Classifier: Intended Audience :: Education
Classifier: Intended Audience :: Science/Research
Classifier: License :: OSI Approved :: MIT License
Classifier: Natural Language :: English
Classifier: Operating System :: OS Independent
Classifier: Programming Language :: Python
Classifier: Programming Language :: Python :: 3.8
Classifier: Topic :: Education
Classifier: Topic :: Software Development :: Libraries :: Python Modules
Classifier: Typing :: Typed
Requires-Python: >=3.8
Requires-Dist: mlxtend
Requires-Dist: pandas
Provides-Extra: testing
Requires-Dist: pytest ; extra == 'testing'
Requires-Dist: pytest-cov ; extra == 'testing'
